TwoToOneMux.v
//2-1 mux that takes selects a when s = 1 and b when s = 0
module TwoToOneMux(a, b, s, out);
    input a;
    input b;
    input s;
    output out;
    assign out = (a & s) | (b & ~s);
endmodule

CalcNextCellState.v
`include "TwoToOneMux.v"

//calculates the next state for a cell given the elementary rule and the current state 
//current state is the value of the cell and its 2 neighbors
module CalcNextCellState(rule, current_state, next_state);
    input [7 : 0] rule;
    input [2 : 0] current_state;
    output next_state;

    wire m1_out;
    TwoToOneMux m1(rule[7], rule[6], current_state[0], m1_out);

    wire m2_out;
    TwoToOneMux m2(rule[5], rule[4], current_state[0], m2_out);

    wire m3_out;
    TwoToOneMux m3(rule[3], rule[2], current_state[0], m3_out);

    wire m4_out;
    TwoToOneMux m4(rule[1], rule[0], current_state[0], m4_out);

    wire m5_out;
    TwoToOneMux m5(m1_out, m2_out, current_state[1], m5_out);

    wire m6_out;
    TwoToOneMux m6(m3_out, m4_out, current_state[1], m6_out);

    TwoToOneMux m7(m5_out, m6_out, current_state[2], next_state);
endmodule

CalcNextCellState_TestBench.v
`timescale 1ns/1ns
`include "CalcNextCellState.v"

module CalcNextCellState_TestBench();
    reg [7 : 0] RULE;
    reg [2 : 0] STATE;
    wire NEXT_STATE;
    CalcNextCellState c(RULE, STATE, NEXT_STATE);

    initial begin
        $dumpfile("./Waveforms/CalcNextCellState_TestBench.vcd");
        $dumpvars(0,  CalcNextCellState_TestBench);
        RULE <= 8'b01101110; STATE <= 3'b111; #5;
        RULE <= 8'b01101110; STATE <= 3'b110; #5;
        RULE <= 8'b01101110; STATE <= 3'b101; #5;
        RULE <= 8'b01101110; STATE <= 3'b100; #5;
        RULE <= 8'b01101110; STATE <= 3'b011; #5;
        RULE <= 8'b01101110; STATE <= 3'b010; #5;
        RULE <= 8'b01101110; STATE <= 3'b001; #5;
        RULE <= 8'b01101110; STATE <= 3'b000; #5;

        RULE <= 8'b01011010; STATE <= 3'b111; #5;
        RULE <= 8'b01011010; STATE <= 3'b110; #5;
        RULE <= 8'b01011010; STATE <= 3'b101; #5;
        RULE <= 8'b01011010; STATE <= 3'b100; #5;
        RULE <= 8'b01011010; STATE <= 3'b011; #5;
        RULE <= 8'b01011010; STATE <= 3'b010; #5;
        RULE <= 8'b01011010; STATE <= 3'b001; #5;
        RULE <= 8'b01011010; STATE <= 3'b000; #5;
    end
endmodule

Waveforms/CalcNextCellState_TestBench.vcd
$date
	Sun Jul  7 21:36:47 2024
$end
$version
	Icarus Verilog
$end
$timescale
	1ns
$end
$scope module CalcNextCellState_TestBench $end
$var wire 1 ! NEXT_STATE $end
$var reg 8 " RULE [7:0] $end
$var reg 3 # STATE [2:0] $end
$scope module c $end
$var wire 3 $ current_state [2:0] $end
$var wire 8 % rule [7:0] $end
$var wire 1 ! next_state $end
$var wire 1 & m6_out $end
$var wire 1 ' m5_out $end
$var wire 1 ( m4_out $end
$var wire 1 ) m3_out $end
$var wire 1 * m2_out $end
$var wire 1 + m1_out $end
$scope module m1 $end
$var wire 1 , a $end
$var wire 1 - b $end
$var wire 1 + out $end
$var wire 1 . s $end
$upscope $end
$scope module m2 $end
$var wire 1 / a $end
$var wire 1 0 b $end
$var wire 1 * out $end
$var wire 1 1 s $end
$upscope $end
$scope module m3 $end
$var wire 1 2 a $end
$var wire 1 3 b $end
$var wire 1 ) out $end
$var wire 1 4 s $end
$upscope $end
$scope module m4 $end
$var wire 1 5 a $end
$var wire 1 6 b $end
$var wire 1 ( out $end
$var wire 1 7 s $end
$upscope $end
$scope module m5 $end
$var wire 1 + a $end
$var wire 1 * b $end
$var wire 1 ' out $end
$var wire 1 8 s $end
$upscope $end
$scope module m6 $end
$var wire 1 ) a $end
$var wire 1 ( b $end
$var wire 1 & out $end
$var wire 1 9 s $end
$upscope $end
$scope module m7 $end
$var wire 1 ' a $end
$var wire 1 & b $end
$var wire 1 ! out $end
$var wire 1 : s $end
$upscope $end
$upscope $end
$upscope $end
$enddefinitions $end
$comment Show the parameter values. $end
$dumpall
$end
#0
$dumpvars
1:
19
18
17
06
15
14
13
12
11
00
1/
1.
1-
0,
0+
1*
1)
1(
0'
1&
b1101110 %
b111 $
b111 #
b1101110 "
0!
$end
#5
1!
1'
1+
0*
0(
0.
01
04
07
b110 #
b110 $
#10
1!
0+
1*
1(
1'
1&
1.
11
14
17
08
09
b101 #
b101 $
#15
0!
0'
0&
1+
0*
0(
0.
01
04
07
b100 #
b100 $
#20
1!
0+
1*
1(
0'
1&
1.
11
14
17
18
19
0:
b11 #
b11 $
#25
1'
1+
0*
0(
0.
01
04
07
b10 #
b10 $
#30
1!
0+
1*
1(
1'
1&
1.
11
14
17
08
09
b1 #
b1 $
#35
0!
0'
0&
1+
0*
0(
0.
01
04
07
b0 #
b0 $
#40
0!
0+
1(
0'
1&
0*
1.
11
14
17
18
19
1:
0/
10
03
b111 #
b111 $
b1011010 "
b1011010 %
#45
1!
1'
0&
1+
1*
0)
0(
0.
01
04
07
b110 #
b110 $
#50
0!
0'
1&
0+
0*
1)
1(
1.
11
14
17
08
09
b101 #
b101 $
#55
1!
1'
0&
1+
1*
0)
0(
0.
01
04
07
b100 #
b100 $
#60
0'
1&
0+
0*
1)
1(
1!
1.
11
14
17
18
19
0:
b11 #
b11 $
#65
0!
1'
0&
1+
1*
0)
0(
0.
01
04
07
b10 #
b10 $
#70
1!
0'
1&
0+
0*
1)
1(
1.
11
14
17
08
09
b1 #
b1 $
#75
0!
1'
0&
1+
1*
0)
0(
0.
01
04
07
b0 #
b0 $
