TwoToOneMux.v
//2-1 mux that takes selects a when s = 1 and b when s = 0
module TwoToOneMux(a, b, s, out);
    input a;
    input b;
    input s;
    output out;
    assign out = (a & s) | (b & ~s);
endmodule

TwoToOneMux_TestBench.v
`timescale 1ns/1ns
`include "TwoToOneMux.v"

module TwoToOneMux_TestBench();
    reg A;
    reg B;
    reg S;
    wire cout;
    TwoToOneMux f(A, B, S, cout);

    initial begin
        $dumpfile("./Waveforms/TwoToOneMux_TestBench.vcd");
        $dumpvars(0,  TwoToOneMux_TestBench);
        A <= 1'b0; B <= 1'b0; S <= 1'b0; #5;
        A <= 1'b0; B <= 1'b0; S <= 1'b1; #5;
        A <= 1'b0; B <= 1'b1; S <= 1'b0; #5;
        A <= 1'b0; B <= 1'b1; S <= 1'b1; #5;
        A <= 1'b1; B <= 1'b0; S <= 1'b0; #5;
        A <= 1'b1; B <= 1'b0; S <= 1'b1; #5;
        A <= 1'b1; B <= 1'b1; S <= 1'b0; #5;
        A <= 1'b1; B <= 1'b1; S <= 1'b1; #5;
    end

endmodule

Waveforms/TwoToOneMux_TestBench.vcd
$date
	Sun Jul  7 21:35:19 2024
$end
$version
	Icarus Verilog
$end
$timescale
	1ns
$end
$scope module TwoToOneMux_TestBench $end
$var wire 1 ! cout $end
$var reg 1 " A $end
$var reg 1 # B $end
$var reg 1 $ S $end
$scope module f $end
$var wire 1 " a $end
$var wire 1 # b $end
$var wire 1 ! out $end
$var wire 1 $ s $end
$upscope $end
$upscope $end
$enddefinitions $end
$comment Show the parameter values. $end
$dumpall
$end
#0
$dumpvars
0$
0#
0"
0!
$end
#5
1$
#10
1!
0$
1#
#15
0!
1$
#20
0$
0#
1"
#25
1!
1$
#30
0$
1#
#35
1$
